hyperbeam/__init__.py
hyperbeam/web_search.py
hyperbeam-0.1.2.dist-info/licenses/LICENSE
hyperbeam-0.1.2.dist-info/METADATA
hyperbeam-0.1.2.dist-info/WHEEL
hyperbeam-0.1.2.dist-info/top_level.txt
hyperbeam-0.1.2.dist-info/RECORD
