Metadata-Version: 2.4
Name: hyperbeam
Version: 0.1.2
Summary: Hyperbeam is a Python library designed to provide intelligent search tooling.
Author-email: Sean McCurdy <sean@hyprbm.com>
License: MIT License
Project-URL: Homepage, https://github.com/hyprbm/hyperbeam
Project-URL: Repository, https://github.com/hyprbm/hyperbeam
Project-URL: Bug Tracker, https://github.com/hyprbm/hyperbeam/issues
Keywords: search,web search,duckduckgo,scraperapi,hyperbeam,intelligent search
Classifier: Development Status :: 3 - Alpha
Classifier: Intended Audience :: Developers
Classifier: License :: OSI Approved :: MIT License
Classifier: Programming Language :: Python :: 3
Classifier: Programming Language :: Python :: 3.10
Classifier: Programming Language :: Python :: 3.11
Classifier: Programming Language :: Python :: 3.12
Classifier: Operating System :: OS Independent
Classifier: Topic :: Internet :: WWW/HTTP :: Indexing/Search
Classifier: Topic :: Software Development :: Libraries :: Python Modules
Requires-Python: >=3.10
License-File: LICENSE
Requires-Dist: duckduckgo-search>=8.0.2
Requires-Dist: scraperapi-sdk>=1.5.3
Requires-Dist: bs4>=0.0.2
Requires-Dist: twine>=6.1.0
Provides-Extra: development
Requires-Dist: black[jupyter]>=25.1.0; extra == "development"
Requires-Dist: flake8>=7.2.0; extra == "development"
Requires-Dist: isort>=6.0.1; extra == "development"
Dynamic: license-file
